Workbook
Name aba2_relatorio_mensal: 'Aba 2'!$A$1:$N$24
Name entrada: 'Aba 2'!$A$5:$A$7
Name investimentos: 'Aba 2'!$A$19:$A$21
Name lista1: 'aba de apoio'!$A$1:$A$10
Name saidas: 'Aba 2'!$A$11:$A$15

Sheet aba1_entrada_dados
A1: ENTRADAS | C1: Data | D1: Descrição | E1: Conta | F1: Valor | G1: Fluxo | H1: Tipo
A2: Venda de Produtos | C2: 46027 | D2: Venda Lote A10 | E2: Venda de Produtos | F2: 15500 | G2: =IF(E2="", "", IF(COUNTIF('Aba 2'!$A$5:$A$7, E2)>0, "Entrada", IF(COUNTIF('Aba 2'!$A$11:$A$15, E2)>0, "Saída", "Investimento"))) -> Entrada | H2: =IF(Tabela1[[#This Row],[Fluxo]]="Investmento","Investimento","Operacional") -> Operacional
A3: Prestação de Serviços | C3: 46032 | D3: Aluguel Escritório | E3: Aluguel e Utilidades | F3: 3200 | G3: =IF(E3="", "", IF(COUNTIF('Aba 2'!$A$5:$A$7, E3)>0, "Entrada", IF(COUNTIF('Aba 2'!$A$11:$A$15, E3)>0, "Saída", "Investimento"))) -> Saída | H3: =IF(Tabela1[[#This Row],[Fluxo]]="Investmento","Investimento","Operacional") -> Operacional
A4: Rendimentos | C4: 46037 | D4: Marketing Digital Jan | E4: Marketing e Vendas | F4: 1200 | G4: =IF(E4="", "", IF(COUNTIF('Aba 2'!$A$5:$A$7, E4)>0, "Entrada", IF(COUNTIF('Aba 2'!$A$11:$A$15, E4)>0, "Saída", "Investimento"))) -> Saída | H4: =IF(Tabela1[[#This Row],[Fluxo]]="Investmento","Investimento","Operacional") -> Operacional
C5: 46042 | D5: Aporte Reserva Mensal | E5: Reserva de Emergência | F5: 1500 | G5: =IF(E5="", "", IF(COUNTIF('Aba 2'!$A$5:$A$7, E5)>0, "Entrada", IF(COUNTIF('Aba 2'!$A$11:$A$15, E5)>0, "Saída", "Investimento"))) -> Investimento | H5: =IF(Tabela1[[#This Row],[Fluxo]]="Investmento","Investimento","Operacional") -> Operacional
A6: SAÍDAS | C6: 46050 | D6: Salários Equipe | E6: Folha de Pagamento | F6: 8500 | G6: =IF(E6="", "", IF(COUNTIF('Aba 2'!$A$5:$A$7, E6)>0, "Entrada", IF(COUNTIF('Aba 2'!$A$11:$A$15, E6)>0, "Saída", "Investimento"))) -> Saída | H6: =IF(Tabela1[[#This Row],[Fluxo]]="Investmento","Investimento","Operacional") -> Operacional
A7: CMV (Fornecedores) | C7: 46058 | D7: Serviço Consultoria B | E7: Prestação de Serviços | F7: 4200 | G7: =IF(E7="", "", IF(COUNTIF('Aba 2'!$A$5:$A$7, E7)>0, "Entrada", IF(COUNTIF('Aba 2'!$A$11:$A$15, E7)>0, "Saída", "Investimento"))) -> Entrada | H7: =IF(Tabela1[[#This Row],[Fluxo]]="Investmento","Investimento","Operacional") -> Operacional
A8: Folha de Pagamento | C8: 46065 | D8: Compra de Insumos | E8: CMV (Fornecedores) | F8: 5400 | G8: =IF(E8="", "", IF(COUNTIF('Aba 2'!$A$5:$A$7, E8)>0, "Entrada", IF(COUNTIF('Aba 2'!$A$11:$A$15, E8)>0, "Saída", "Investimento"))) -> Saída | H8: =IF(Tabela1[[#This Row],[Fluxo]]="Investmento","Investimento","Operacional") -> Operacional
A9: Marketing e Vendas | C9: 46081 | D9: Impostos Simples Nacional | E9: Impostos e Taxas | F9: 1100 | G9: =IF(E9="", "", IF(COUNTIF('Aba 2'!$A$5:$A$7, E9)>0, "Entrada", IF(COUNTIF('Aba 2'!$A$11:$A$15, E9)>0, "Saída", "Investimento"))) -> Saída | H9: =IF(Tabela1[[#This Row],[Fluxo]]="Investmento","Investimento","Operacional") -> Operacional
A10: Impostos e Taxas | C10: 46155 | D10: Impostos Simples Nacional | E10: Impostos e Taxas | F10: 100 | G10: =IF(E10="", "", IF(COUNTIF('Aba 2'!$A$5:$A$7, E10)>0, "Entrada", IF(COUNTIF('Aba 2'!$A$11:$A$15, E10)>0, "Saída", "Investimento"))) -> Saída | H10: =IF(Tabela1[[#This Row],[Fluxo]]="Investmento","Investimento","Operacional") -> Operacional
A11: Aluguel e Utilidades | C11: 46155 | D11: Impostos Simples Nacional | E11: Reserva de Emergência | F11: 10 | G11: =IF(E11="", "", IF(COUNTIF('Aba 2'!$A$5:$A$7, E11)>0, "Entrada", IF(COUNTIF('Aba 2'!$A$11:$A$15, E11)>0, "Saída", "Investimento"))) -> Investimento | H11: =IF(Tabela1[[#This Row],[Fluxo]]="Investmento","Investimento","Operacional") -> Operacional
C12: 46160 | D12: Impostos Simples Nacional | E12: Reserva de Emergência | F12: 18 | G12: =IF(E12="", "", IF(COUNTIF('Aba 2'!$A$5:$A$7, E12)>0, "Entrada", IF(COUNTIF('Aba 2'!$A$11:$A$15, E12)>0, "Saída", "Investimento"))) -> Investimento
A13: INVESTIMENTOS | G13: =IF(E13="", "", IF(COUNTIF('Aba 2'!$A$5:$A$7, E13)>0, "Entrada", IF(COUNTIF('Aba 2'!$A$11:$A$15, E13)>0, "Saída", "Investimento")))
A14: Reserva de Emergência | G14: =IF(E14="", "", IF(COUNTIF('Aba 2'!$A$5:$A$7, E14)>0, "Entrada", IF(COUNTIF('Aba 2'!$A$11:$A$15, E14)>0, "Saída", "Investimento")))
A15: Expansão/Novos Ativos | G15: =IF(E15="", "", IF(COUNTIF('Aba 2'!$A$5:$A$7, E15)>0, "Entrada", IF(COUNTIF('Aba 2'!$A$11:$A$15, E15)>0, "Saída", "Investimento")))
G16: =IF(E16="", "", IF(COUNTIF('Aba 2'!$A$5:$A$7, E16)>0, "Entrada", IF(COUNTIF('Aba 2'!$A$11:$A$15, E16)>0, "Saída", "Investimento")))
G17: =IF(E17="", "", IF(COUNTIF('Aba 2'!$A$5:$A$7, E17)>0, "Entrada", IF(COUNTIF('Aba 2'!$A$11:$A$15, E17)>0, "Saída", "Investimento")))
G18: =IF(E18="", "", IF(COUNTIF('Aba 2'!$A$5:$A$7, E18)>0, "Entrada", IF(COUNTIF('Aba 2'!$A$11:$A$15, E18)>0, "Saída", "Investimento")))

Sheet Aba 2
A1: Categoria | B1: Janeiro | C1: Fevereiro | D1: Março | E1: Abril | F1: Maio | G1: Junho | H1: Julho | I1: Agosto | J1: Setembro | K1: Outubro | L1: Novembro | M1: Dezembro | N1: Consolidado
A2: Saldo Inicial do Caixa | B2: 0
A4: ENTRADAS (Receitas)
A5: Venda de Produtos
A6: Prestação de Serviços
A7: Rendimentos
A8: Total de Entradas
A10: SAÍDAS (Despesas)
A11: CMV (Fornecedores)
A12: Folha de Pagamento
A13: Marketing e Vendas
A14: Impostos e Taxas
A15: Aluguel e Utilidades
A16: Total de Saídas
... A24: SALDO ACUMULADO (Saldo Inicial + Resultado)

Sheet aba de apoio
A1: Venda de Produtos
A2: Prestação de Serviços
A3: Rendimentos
A4: CMV (Fornecedores)
A5: Folha de Pagamento
A6: Marketing e Vendas
A7: Impostos e Taxas
A8: Aluguel e Utilidades
A9: Reserva de Emergência
A10: Expansão/Novos Ativos
